ctorch/__init__.py
ctorch/nn/__init__.py
ctorch/nn/common_types.py
ctorch/nn/functional.py
ctorch/nn/modules/__init__.py
ctorch/nn/modules/conv.py
ctorch/nn/modules/init.py
ctorch/nn/modules/linear.py
ctorch/nn/modules/utils.py
ctorch-0.3.0.dist-info/LICENSE.md
ctorch-0.3.0.dist-info/WHEEL
ctorch-0.3.0.dist-info/METADATA
ctorch-0.3.0.dist-info/RECORD
