Metadata-Version: 2.1
Name: ctorch
Version: 0.3.0
Summary: Complex Neural Networks for PyTorch
License: MIT
Author: Miller Wilt
Author-email: miller@pyriteai.com
Requires-Python: >=3.6.1,<4.0.0
Classifier: License :: OSI Approved :: MIT License
Classifier: Programming Language :: Python :: 3
Classifier: Programming Language :: Python :: 3.7
Classifier: Programming Language :: Python :: 3.8
Requires-Dist: torch (>=1.5.1,<2.0.0)
